stegaplots/__init__.py
stegaplots/__main__.py
stegaplots/stegano.py
stegaplots-0.2.1.dist-info/LICENSE
stegaplots-0.2.1.dist-info/METADATA
stegaplots-0.2.1.dist-info/WHEEL
stegaplots-0.2.1.dist-info/entry_points.txt
stegaplots-0.2.1.dist-info/top_level.txt
stegaplots-0.2.1.dist-info/RECORD
