Metadata-Version: 2.1
Name: stegaplots
Version: 0.2.1
Summary: Store plot related information INSIDE the plot itself.
Author-email: lfrati <lfrati.github@gmail.com>
License: MIT
Project-URL: Homepage, https://github.com/lfrati/stegaplots
Keywords: steganography,matplotlib
Classifier: License :: OSI Approved :: MIT License
Classifier: Programming Language :: Python :: 3
Requires-Python: >=3.9
License-File: LICENSE
Requires-Dist: matplotlib
Requires-Dist: numpy
Requires-Dist: numba
Requires-Dist: tqdm
Provides-Extra: dev
Requires-Dist: tqdm ; extra == 'dev'
Requires-Dist: bumpver ; extra == 'dev'
Requires-Dist: pip-tools ; extra == 'dev'
Requires-Dist: build ; extra == 'dev'
Requires-Dist: twine ; extra == 'dev'
Requires-Dist: pytest ; extra == 'dev'
